LICENSE
README.md
setup.py
tgbot_ping/__init__.py
tgbot_ping.egg-info/PKG-INFO
tgbot_ping.egg-info/SOURCES.txt
tgbot_ping.egg-info/dependency_links.txt
tgbot_ping.egg-info/requires.txt
tgbot_ping.egg-info/top_level.txt